Metadata-Version: 2.1
Name: cima-comutations-factors-5
Version: 0.0.1
Summary: Provide comutations factors based on CIMA H mortability table
Home-page: https://github.com/Hariost/cima
Author: HARIOST
Author-email: hrvhounkanrin@gmail.com
License: UNKNOWN
Project-URL: Bug Tracker, https://github.com/pypa/sampleproject/issues
Platform: UNKNOWN
Classifier: Programming Language :: Python :: 3
Classifier: License :: OSI Approved :: MIT License
Classifier: Operating System :: OS Independent
Requires-Python: >=3.6
License-File: LICENSE
